Workbook

Sheet Original S1
A1: Transaction ID | B1: Date | C1: Country | D1: City | E1: Category ID | F1: Category Name | G1: Cost | H1: Price (Analysis) | I1: Unique Countries | J1: Unique countries count | K1: unique cities | L1: unique cities count | M1: Software Licenses | O1: 1st two letters | P1: last two letters | Q1: Find Letter | R1: Find next 3 letter
A2: TXN-1001 | B2: 45306 | C2: United States | D2: New York | E2: CAT-101 | F2: =VLOOKUP(E2,'S2'!$A$2:$B$26,2,false) -> Cloud & IT Infrastructure | G2: 4250 | H2: =if(G2>1000, "Expensive", "Cheep") -> Expensive | I2: {=UNIQUE(C2:C26)} -> United States | J2: =IFERROR(__xludf.DUMMYFUNCTION("countunique(C2:C26)"),9.0) -> 9 | K2: {=unique(D2:D26)} -> New York | L2: =IFERROR(__xludf.DUMMYFUNCTION("COUNTUNIQUE(D2:D26)"),17.0) -> 17 | M2: =sumif(F2:F26,M1,G2:G26) -> 5580 | O2: =left(C2,3) -> Uni | P2: =RIGHT(K2,2) -> rk | Q2: =find("e",C2) -> 5 | R2: =mid(F2,2,3) -> lou
A3: TXN-1002 | B3: 45307 | C3: United Kingdom | D3: London | E3: CAT-102 | F3: =VLOOKUP(E3,'S2'!$A$2:$B$26,2,false) -> Marketing & Advertising | G3: 3100.5 | H3: =if(G3>1000, "Expensive", "Cheep") -> Expensive | I3: United Kingdom | K3: London | O3: =left(C3,3) -> Uni | P3: =RIGHT(D3,2) -> on | Q3: =find("e",C3) -> 5 | R3: =mid(F3,2,3) -> ark
A4: TXN-1003 | B4: 45308 | C4: Germany | D4: Berlin | E4: CAT-103 | F4: =VLOOKUP(E4,'S2'!$A$2:$B$26,2,false) -> Travel & Entertainment | G4: 1240.75 | H4: =if(G4>1000, "Expensive", "Cheep") -> Expensive | I4: Germany | K4: Berlin | M4: Software Licenses | O4: =left(C4,3) -> Ger | P4: =RIGHT(D4,2) -> in | Q4: =find("e",C4) -> 2 | R4: =mid(F4,2,3) -> rav
A5: TXN-1004 | B5: 45309 | C5: Japan | D5: Tokyo | E5: CAT-106 | F5: =VLOOKUP(E5,'S2'!$A$2:$B$26,2,false) -> Software Licenses | G5: 850 | H5: =if(G5>1000, "Expensive", "Cheep") -> Cheep | I5: Japan | K5: Tokyo | M5: Country cost on software licenses | O5: =left(C5,3) -> Jap | P5: =RIGHT(D5,2) -> yo | Q5: =find("e",C5) -> #VALUE! | R5: =mid(F5,2,3) -> oft
A6: TXN-1005 | B6: 45310 | C6: United States | D6: San Francisco | E6: CAT-105 | F6: =VLOOKUP(E6,'S2'!$A$2:$B$26,2,false) -> Professional Services | G6: 6400 | H6: =if(G6>1000, "Expensive", "Cheep") -> Expensive | I6: Canada | K6: San Francisco | M6: =sumif(C2:C26,C5,G2:G26) -> 2950.25 | O6: =left(C6,3) -> Uni | P6: =RIGHT(D6,2) -> co | Q6: =find("e",C6) -> 5 | R6: =mid(F6,2,3) -> rof
A7: TXN-1006 | B7: 45311 | C7: Canada | D7: Toronto | E7: CAT-104 | F7: =VLOOKUP(E7,'S2'!$A$2:$B$26,2,false) -> Office Supplies | G7: 420.3 | H7: =if(G7>1000, "Expensive", "Cheep") -> Cheep | I7: France | K7: Toronto | O7: =left(C7,3) -> Can | P7: =RIGHT(D7,2) -> to | Q7: =find("e",C7) -> #VALUE! | R7: =mid(F7,2,3) -> ffi
A8: TXN-1007 | B8: 45312 | C8: France | D8: Paris | E8: CAT-103 | F8: =VLOOKUP(E8,'S2'!$A$2:$B$26,2,false) -> Travel & Entertainment | G8: 1850 | H8: =if(G8>1000, "Expensive", "Cheep") -> Expensive | I8: Singapore | K8: Paris | O8: =left(C8,3) -> Fra | P8: =RIGHT(D8,2) -> is | Q8: =find("e",C8) -> 6 | R8: =mid(F8,2,3) -> rav
A9: TXN-1008 | B9: 45313 | C9: Singapore | D9: Singapore | E9: CAT-101 | F9: =VLOOKUP(E9,'S2'!$A$2:$B$26,2,false) -> Cloud & IT Infrastructure | G9: 5120 | H9: =if(G9>1000, "Expensive", "Cheep") -> Expensive | I9: Australia | K9: Singapore | M9: Germany | N9: Travel & Entertainment | O9: =left(C9,3) -> Sin | P9: =RIGHT(D9,2) -> re | Q9: =find("e",C9) -> 9 | R9: =mid(F9,2,3) -> lou
A10: TXN-1009 | B10: 45314 | C10: Australia | D10: Sydney | E10: CAT-102 | F10: =VLOOKUP(E10,'S2'!$A$2:$B$26,2,false) -> Marketing & Advertising | G10: 2750 | H10: =if(G10>1000, "Expensive", "Cheep") -> Expensive | I10: Netherlands | K10: Sydney | O10: =left(C10,3) -> Aus | P10: =RIGHT(D10,2) -> ey | Q10: =find("e",C10) -> #VALUE! | R10: =mid(F10,2,3) -> ark
A11: TXN-1010 | B11: 45315 | C11: United States | D11: Austin | E11: CAT-106 | F11: =VLOOKUP(E11,'S2'!$A$2:$B$26,2,false) -> Software Licenses | G11: 1450 | H11: =if(G11>1000, "Expensive", "Cheep") -> Expensive | K11: Austin | O11: =left(C11,3) -> Uni | P11: =RIGHT(D11,2) -> in | Q11: =find("e",C11) -> 5 | R11: =mid(F11,2,3) -> oft
A12: TXN-1011 | B12: 45316 | C12: Germany | D12: Munich | E12: CAT-105 | F12: =VLOOKUP(E12,'S2'!$A$2:$B$26,2,false) -> Professional Services | G12: 7200 | H12: =if(G12>1000, "Expensive", "Cheep") -> Expensive | K12: Munich | M12: =sumifs(G2:G26,C2:C26,M9,F2:F26,N9) -> 1240.75 | O12: =left(C12,3) -> Ger | P12: =RIGHT(D12,2) -> ch | Q12: =find("e",C12) -> 2 | R12: =mid(F12,2,3) -> rof
A13: TXN-1012 | B13: 45317 | C13: United Kingdom | D13: Manchester | E13: CAT-104 | F13: =VLOOKUP(E13,'S2'!$A$2:$B$26,2,false) -> Office Supplies | G13: 630.5 | H13: =if(G13>1000, "Expensive", "Cheep") -> Cheep | K13: Manchester | O13: =left(C13,3) -> Uni | P13: =RIGHT(D13,2) -> er | Q13: =find("e",C13) -> 5 | R13: =mid(F13,2,3) -> ffi
A14: TXN-1013 | B14: 45318 | C14: Netherlands | D14: Amsterdam | E14: CAT-102 | F14: =VLOOKUP(E14,'S2'!$A$2:$B$26,2,false) -> Marketing & Advertising | G14: 4100 | H14: =if(G14>1000, "Expensive", "Cheep") -> Expensive | K14: Amsterdam | N14: New York | O14: =left(C14,3) -> Net | P14: =RIGHT(D14,2) -> am | Q14: =find("e",C14) -> 2 | R14: =mid(F14,2,3) -> ark
A15: TXN-1014 | B15: 45319 | C15: Japan | D15: Osaka | E15: CAT-103 | F15: =VLOOKUP(E15,'S2'!$A$2:$B$26,2,false) -> Travel & Entertainment | G15: 2100.25 | H15: =if(G15>1000, "Expensive", "Cheep") -> Expensive | K15: Osaka | O15: =left(C15,3) -> Jap | P15: =RIGHT(D15,2) -> ka | Q15: =find("e",C15) -> #VALUE! | R15: =mid(F15,2,3) -> rav
A16: TXN-1015 | B16: 45320 | C16: United States | D16: Chicago | E16: CAT-101 | F16: =VLOOKUP(E16,'S2'!$A$2:$B$26,2,false) -> Cloud & IT Infrastructure | G16: 3890 | H16: =if(G16>1000, "Expensive", "Cheep") -> Expensive | K16: Chicago | M16: new york work on how many criteria | O16: =left(C16,3) -> Uni | P16: =RIGHT(D16,2) -> go | Q16: =find("e",C16) -> 5 | R16: =mid(F16,2,3) -> lou
A17: TXN-1016 | B17: 45321 | C17: Canada | D17: Vancouver | E17: CAT-106 | F17: =VLOOKUP(E17,'S2'!$A$2:$B$26,2,false) -> Software Licenses | G17: 980 | H17: =if(G17>1000, "Expensive", "Cheep") -> Cheep | K17: Vancouver | M17: =countif(D2:D26,N14) -> 2 | O17: =left(C17,3) -> Can | P17: =RIGHT(D17,2) -> er | Q17: =find("e",C17) -> #VALUE! | R17: =mid(F17,2,3) -> oft
A18: TXN-1017 | B18: 45322 | C18: United Kingdom | D18: London | E18: CAT-105 | F18: =VLOOKUP(E18,'S2'!$A$2:$B$26,2,false) -> Professional Services | G18: 5500 | H18: =if(G18>1000, "Expensive", "Cheep") -> Expensive | K18: Melbourne | O18: =left(C18,3) -> Uni | P18: =RIGHT(D18,2) -> on | Q18: =find("e",C18) -> 5 | R18: =mid(F18,2,3) -> rof
A19: TXN-1018 | B19: 45323 | C19: Australia | D19: Melbourne | E19: CAT-104 | F19: =VLOOKUP(E19,'S2'!$A$2:$B$26,2,false) -> Office Supplies | G19: 315.8 | H19: =if(G19>1000, "Expensive", "Cheep") -> Cheep | O19: =left(C19,3) -> Aus | P19: =RIGHT(D19,2) -> ne | Q19: =find("e",C19) -> #VALUE! | R19: =mid(F19,2,3) -> ffi
A20: TXN-1019 | B20: 45324 | C20: United States | D20: New York | E20: CAT-102 | F20: =VLOOKUP(E20,'S2'!$A$2:$B$26,2,false) -> Marketing & Advertising | G20: 6800 | H20: =if(G20>1000, "Expensive", "Cheep") -> Expensive | O20: =left(C20,3) -> Uni | P20: =RIGHT(D20,2) -> rk | Q20: =find("e",C20) -> 5 | R20: =mid(F20,2,3) -> ark
A21: TXN-1020 | B21: 45325 | C21: Germany | D21: Berlin | E21: CAT-101 | F21: =VLOOKUP(E21,'S2'!$A$2:$B$26,2,false) -> Cloud & IT Infrastructure | G21: 4750 | H21: =if(G21>1000, "Expensive", "Cheep") -> Expensive | O21: =left(C21,3) -> Ger | P21: =RIGHT(D21,2) -> in | Q21: =find("e",C21) -> 2 | R21: =mid(F21,2,3) -> lou
A22: TXN-1021 | B22: 45326 | C22: France | D22: Paris | E22: CAT-105 | F22: =VLOOKUP(E22,'S2'!$A$2:$B$26,2,false) -> Professional Services | G22: 3900 | H22: =if(G22>1000, "Expensive", "Cheep") -> Expensive | O22: =left(C22,3) -> Fra | P22: =RIGHT(D22,2) -> is | Q22: =find("e",C22) -> 6 | R22: =mid(F22,2,3) -> rof
A23: TXN-1022 | B23: 45327 | C23: Singapore | D23: Singapore | E23: CAT-103 | F23: =VLOOKUP(E23,'S2'!$A$2:$B$26,2,false) -> Travel & Entertainment | G23: 1680.4 | H23: =if(G23>1000, "Expensive", "Cheep") -> Expensive | O23: =left(C23,3) -> Sin | P23: =RIGHT(D23,2) -> re | Q23: =find("e",C23) -> 9 | R23: =mid(F23,2,3) -> rav
A24: TXN-1023 | B24: 45328 | C24: United States | D24: San Francisco | E24: CAT-106 | F24: =VLOOKUP(E24,'S2'!$A$2:$B$26,2,false) -> Software Licenses | G24: 2300 | H24: =if(G24>1000, "Expensive", "Cheep") -> Expensive | O24: =left(C24,3) -> Uni | P24: =RIGHT(D24,2) -> co | Q24: =find("e",C24) -> 5 | R24: =mid(F24,2,3) -> oft
A25: TXN-1024 | B25: 45329 | C25: Netherlands | D25: Amsterdam | E25: CAT-104 | F25: =VLOOKUP(E25,'S2'!$A$2:$B$26,2,false) -> Office Supplies | G25: 540 | H25: =if(G25>1000, "Expensive", "Cheep") -> Cheep | O25: =left(C25,3) -> Net | P25: =RIGHT(D25,2) -> am | Q25: =find("e",C25) -> 2 | R25: =mid(F25,2,3) -> ffi
A26: TXN-1025 | B26: 45330 | C26: United Kingdom | D26: London | E26: CAT-101 | F26: =VLOOKUP(E26,'S2'!$A$2:$B$26,2,false) -> Cloud & IT Infrastructure | G26: 5950 | H26: =if(G26>1000, "Expensive", "Cheep") -> Expensive | O26: =left(C26,3) -> Uni | P26: =RIGHT(D26,2) -> on | Q26: =find("e",C26) -> 5 | R26: =mid(F26,2,3) -> lou

Sheet unique countries
A1: Transaction ID | B1: Date | C1: Country | D1: City | E1: Category ID | F1: Category Name | G1: Cost | H1: day | I1: month | K1: concatenation
A2: TXN-1001 | B2: 45306 | C2: United States | D2: New York | E2: CAT-101 | F2: Cloud & IT Infrastructure | G2: 4250 | I2: =MONTH(B2) -> 1 | J2: =MONTH(C2) -> #VALUE!
A3: TXN-1002 | B3: 45307 | C3: United Kingdom | D3: London | E3: CAT-102 | F3: Marketing & Advertising | G3: 3100.5 | I3: =MONTH(B3) -> 1
A4: TXN-1003 | B4: 45308 | C4: Germany | D4: Berlin | E4: CAT-103 | F4: Travel & Entertainment | G4: 1240.75 | I4: =MONTH(B4) -> 1
A5: TXN-1004 | B5: 45309 | C5: Japan | D5: Tokyo | E5: CAT-106 | F5: Software Licenses | G5: 850 | I5: =MONTH(B5) -> 1
A6: TXN-1005 | B6: 45310 | C6: United States | D6: San Francisco | E6: CAT-105 | F6: Professional Services | G6: 6400 | I6: =MONTH(B6) -> 1
A7: TXN-1006 | B7: 45311 | C7: Canada | D7: Toronto | E7: CAT-104 | F7: Office Supplies | G7: 420.3 | I7: =MONTH(B7) -> 1
A8: TXN-1007 | B8: 45312 | C8: France | D8: Paris | E8: CAT-103 | F8: Travel & Entertainment | G8: 1850 | I8: =MONTH(B8) -> 1 | J8: approach 1 | K8: =CONCATENATE(D8,"-",F8) -> Paris-Travel & Entertainment
A9: TXN-1008 | B9: 45313 | C9: Singapore | D9: Singapore | E9: CAT-101 | F9: Cloud & IT Infrastructure | G9: 5120 | I9: =MONTH(B9) -> 1
A10: TXN-1009 | B10: 45314 | C10: Australia | D10: Sydney | E10: CAT-102 | F10: Marketing & Advertising | G10: 2750 | I10: =MONTH(B10) -> 1
A11: TXN-1010 | B11: 45315 | C11: United States | D11: Austin | E11: CAT-106 | F11: Software Licenses | G11: 1450 | I11: =MONTH(B11) -> 1
A12: TXN-1011 | B12: 45316 | C12: Germany | D12: Munich | E12: CAT-105 | F12: Professional Services | G12: 7200 | I12: =MONTH(B12) -> 1 | J12: approach 2 | K12: =D8&"-"&F8 -> Paris-Travel & Entertainment
A13: TXN-1012 | B13: 45317 | C13: United Kingdom | D13: Manchester | E13: CAT-104 | F13: Office Supplies | G13: 630.5 | I13: =MONTH(B13) -> 1
A14: TXN-1013 | B14: 45318 | C14: Netherlands | D14: Amsterdam | E14: CAT-102 | F14: Marketing & Advertising | G14: 4100 | I14: =MONTH(B14) -> 1
A15: TXN-1014 | B15: 45319 | C15: Japan | D15: Osaka | E15: CAT-103 | F15: Travel & Entertainment | G15: 2100.25 | I15: =MONTH(B15) -> 1
A16: TXN-1015 | B16: 45320 | C16: United States | D16: Chicago | E16: CAT-101 | F16: Cloud & IT Infrastructure | G16: 3890 | I16: =MONTH(B16) -> 1
A17: TXN-1016 | B17: 45321 | C17: Canada | D17: Vancouver | E17: CAT-106 | F17: Software Licenses | G17: 980 | I17: =MONTH(B17) -> 1
A18: TXN-1017 | B18: 45322 | C18: United Kingdom | D18: London | E18: CAT-105 | F18: Professional Services | G18: 5500 | I18: =MONTH(B18) -> 1
A19: TXN-1018 | B19: 45323 | C19: Australia | D19: Melbourne | E19: CAT-104 | F19: Office Supplies | G19: 315.8 | I19: =MONTH(B19) -> 2
A20: TXN-1019 | B20: 45324 | C20: United States | D20: New York | E20: CAT-102 | F20: Marketing & Advertising | G20: 6800 | I20: =MONTH(B20) -> 2
A21: TXN-1020 | B21: 45325 | C21: Germany | D21: Berlin | E21: CAT-101 | F21: Cloud & IT Infrastructure | G21: 4750 | I21: =MONTH(B21) -> 2
A22: TXN-1021 | B22: 45326 | C22: France | D22: Paris | E22: CAT-105 | F22: Professional Services | G22: 3900 | I22: =MONTH(B22) -> 2
A23: TXN-1022 | B23: 45327 | C23: Singapore | D23: Singapore | E23: CAT-103 | F23: Travel & Entertainment | G23: 1680.4 | I23: =MONTH(B23) -> 2
A24: TXN-1023 | B24: 45328 | C24: United States | D24: San Francisco | E24: CAT-106 | F24: Software Licenses | G24: 2300 | I24: =MONTH(B24) -> 2
... A26: TXN-1025 | B26: 45330 | C26: United Kingdom | D26: London | E26: CAT-101 | F26: Cloud & IT Infrastructure | G26: 5950 | I26: =MONTH(B26) -> 2
A31: Transaction ID | B31: Date | C31: Country | D31: City | E31: Category ID | F31: Category Name | G31: Cost | I31: =IFERROR(__xludf.DUMMYFUNCTION("COUNTUNIQUE(B32:B38)"),7.0) -> 7
A32: TXN-1003 | B32: 45308 | C32: Germany | D32: Berlin | E32: CAT-103 | F32: Travel & Entertainment | G32: 1240.75
A33: TXN-1007 | B33: 45312 | C33: France | D33: Paris | E33: CAT-103 | F33: Travel & Entertainment | G33: 1850
A34: TXN-1011 | B34: 45316 | C34: Germany | D34: Munich | E34: CAT-105 | F34: Professional Services | G34: 7200
A35: TXN-1013 | B35: 45318 | C35: Netherlands | D35: Amsterdam | E35: CAT-102 | F35: Marketing & Advertising | G35: 4100
A36: TXN-1020 | B36: 45325 | C36: Germany | D36: Berlin | E36: CAT-101 | F36: Cloud & IT Infrastructure | G36: 4750
A37: TXN-1021 | B37: 45326 | C37: France | D37: Paris | E37: CAT-105 | F37: Professional Services | G37: 3900
A38: TXN-1024 | B38: 45329 | C38: Netherlands | D38: Amsterdam | E38: CAT-104 | F38: Office Supplies | G38: 540

Sheet month cost in %age

Sheet translation
A1: United Kingdom
A3: =IFERROR(__xludf.DUMMYFUNCTION("GOOGLETRANSLATE(A1,""en"",""es"")"),"Reino Unido") -> Reino Unido
A4: Thanks for your interest in the topic.
A5: As next steps, may I suggest that you draft a 1-2 page proposal of your ideas and how they would align with the topic. You can see my publications, projects, and topics here: www.paul-harvey.org . After this, we can continue the discussion.
A6: Regarding Funding, if you are able to provide your own funding, please let me know by replying to this email. If not, then this becomes a competitively funded position. A number of links to possible funding sources are available ( http://www.paul-harvey.org/opportunities/phds/). Please also consider which one would be most relevant for your situation as well as associated deadlines.
A7: Best,
A8: Paul
A10: From: Ameer Hamza <ameerhamzapu838@gmail.com>
A11: Sent: 15 September 2026 07:43
A12: To: Paul Harvey <Paul.Harvey@glasgow.ac.uk> | H12: =IFERROR(__xludf.DUMMYFUNCTION("GOOGLETRANSLATE(A6,""en"",""ur"")"),"فنڈنگ ​​کے حوالے سے، اگر آپ خود اپنی فنڈنگ ​​فراہم کر سکتے ہیں، تو براہ کرم مجھے اس ای میل کا جواب دے کر بتائیں۔ اگر نہیں، تو یہ مسابقتی طور پر فنڈ والی پوزیشن بن جاتی ہے۔ ممکنہ فنڈنگ ​​کے ذرائع کے متعدد لنکس دستیاب ہیں ( http://www.paul-harvey.org/opport"&"unities/phds/)۔ براہ کرم اس بات پر بھی غور کریں کہ آپ کی صورت حال کے ساتھ ساتھ متعلقہ ڈیڈ لائن کے لیے کون سا سب سے زیادہ متعلقہ ہوگا۔") -> فنڈنگ ​​کے حوالے سے، اگر آپ خود اپنی فنڈنگ ​​فراہم کر سکتے ہیں، تو براہ کرم مجھے اس ای میل کا جواب دے کر بتائیں۔ اگر نہیں، تو یہ مسابقتی طور پر فنڈ والی پوزیشن بن جاتی ہے۔ ممکنہ فنڈنگ ​​کے ذرائع کے متعدد لنکس دستیاب ہیں ( http://www.paul-harvey.org/opportunities/phds/)۔ براہ کرم اس بات پر بھی غور کریں کہ آپ کی صورت حال کے ساتھ ساتھ متعلقہ ڈیڈ لائن کے لیے کون سا سب سے زیادہ متعلقہ ہوگا۔
A13: Subject: Prospective MS/direct PHD Student research Interest opportunities
B14: You don't often get email from ameerhamzapu838@gmail.com. Learn why this is important
A15: ...
A17: [Message clipped] View entire message
A18: Dear Dr. Paul,
A20: Thank you for your response and for sharing these details.
A22: Regarding the funding, I am currently on a fully funded scholarship provided by the government of Pakistan for my studies.
A24: I appreciate the suggestion to draft a proposal. I will work on a 1-2 page document outlining my ideas in alignment with your research and will share it with you once it is ready.
A26: Best regards,
A28: Ameer Hamza

Sheet chart
A1: City | B1: Cost
A2: New York | B2: 4250
A3: London | B3: 3100.5
A4: Berlin | B4: 1240.75
A5: Tokyo | B5: 850
A6: San Francisco | B6: 6400
A7: Toronto | B7: 420.3
A8: Paris | B8: 1850
A9: Singapore | B9: 5120
A10: Sydney | B10: 2750
A11: Austin | B11: 1450
A12: Munich | B12: 7200
A13: Manchester | B13: 630.5
... A26: London | B26: 5950

Sheet data filter for specific countr
A1: Transaction ID | B1: Date | C1: Country | D1: City | E1: Category ID | F1: Category Name | G1: Cost
A2: TXN-1001 | B2: 45306 | C2: United States | D2: New York | E2: CAT-101 | F2: Cloud & IT Infrastructure | G2: 4250
A3: TXN-1002 | B3: 45307 | C3: United Kingdom | D3: London | E3: CAT-102 | F3: Marketing & Advertising | G3: 3100.5 | I3: =IFERROR(__xludf.DUMMYFUNCTION("FILTER(A2:G26,C2:C26=""Germany"")"),"TXN-1003") -> TXN-1003 | J3: =IFERROR(__xludf.DUMMYFUNCTION("""COMPUTED_VALUE"""),45308.0) -> 45308 | K3: =IFERROR(__xludf.DUMMYFUNCTION("""COMPUTED_VALUE"""),"Germany") -> Germany | L3: =IFERROR(__xludf.DUMMYFUNCTION("""COMPUTED_VALUE"""),"Berlin") -> Berlin | M3: =IFERROR(__xludf.DUMMYFUNCTION("""COMPUTED_VALUE"""),"CAT-103") -> CAT-103 | N3: =IFERROR(__xludf.DUMMYFUNCTION("""COMPUTED_VALUE"""),"Travel & Entertainment") -> Travel & Entertainment | O3: =IFERROR(__xludf.DUMMYFUNCTION("""COMPUTED_VALUE"""),1240.75) -> 1240.75
A4: TXN-1003 | B4: 45308 | C4: Germany | D4: Berlin | E4: CAT-103 | F4: Travel & Entertainment | G4: 1240.75 | I4: =IFERROR(__xludf.DUMMYFUNCTION("""COMPUTED_VALUE"""),"TXN-1011") -> TXN-1011 | J4: =IFERROR(__xludf.DUMMYFUNCTION("""COMPUTED_VALUE"""),45316.0) -> 45316 | K4: =IFERROR(__xludf.DUMMYFUNCTION("""COMPUTED_VALUE"""),"Germany") -> Germany | L4: =IFERROR(__xludf.DUMMYFUNCTION("""COMPUTED_VALUE"""),"Munich") -> Munich | M4: =IFERROR(__xludf.DUMMYFUNCTION("""COMPUTED_VALUE"""),"CAT-105") -> CAT-105 | N4: =IFERROR(__xludf.DUMMYFUNCTION("""COMPUTED_VALUE"""),"Professional Services") -> Professional Services | O4: =IFERROR(__xludf.DUMMYFUNCTION("""COMPUTED_VALUE"""),7200.0) -> 7200
A5: TXN-1004 | B5: 45309 | C5: Japan | D5: Tokyo | E5: CAT-106 | F5: Software Licenses | G5: 850 | I5: =IFERROR(__xludf.DUMMYFUNCTION("""COMPUTED_VALUE"""),"TXN-1020") -> TXN-1020 | J5: =IFERROR(__xludf.DUMMYFUNCTION("""COMPUTED_VALUE"""),45325.0) -> 45325 | K5: =IFERROR(__xludf.DUMMYFUNCTION("""COMPUTED_VALUE"""),"Germany") -> Germany | L5: =IFERROR(__xludf.DUMMYFUNCTION("""COMPUTED_VALUE"""),"Berlin") -> Berlin | M5: =IFERROR(__xludf.DUMMYFUNCTION("""COMPUTED_VALUE"""),"CAT-101") -> CAT-101 | N5: =IFERROR(__xludf.DUMMYFUNCTION("""COMPUTED_VALUE"""),"Cloud & IT Infrastructure") -> Cloud & IT Infrastructure | O5: =IFERROR(__xludf.DUMMYFUNCTION("""COMPUTED_VALUE"""),4750.0) -> 4750
A6: TXN-1005 | B6: 45310 | C6: United States | D6: San Francisco | E6: CAT-105 | F6: Professional Services | G6: 6400
A7: TXN-1006 | B7: 45311 | C7: Canada | D7: Toronto | E7: CAT-104 | F7: Office Supplies | G7: 420.3
A8: TXN-1007 | B8: 45312 | C8: France | D8: Paris | E8: CAT-103 | F8: Travel & Entertainment | G8: 1850
A9: TXN-1008 | B9: 45313 | C9: Singapore | D9: Singapore | E9: CAT-101 | F9: Cloud & IT Infrastructure | G9: 5120
A10: TXN-1009 | B10: 45314 | C10: Australia | D10: Sydney | E10: CAT-102 | F10: Marketing & Advertising | G10: 2750
A11: TXN-1010 | B11: 45315 | C11: United States | D11: Austin | E11: CAT-106 | F11: Software Licenses | G11: 1450
A12: TXN-1011 | B12: 45316 | C12: Germany | D12: Munich | E12: CAT-105 | F12: Professional Services | G12: 7200
A13: TXN-1012 | B13: 45317 | C13: United Kingdom | D13: Manchester | E13: CAT-104 | F13: Office Supplies | G13: 630.5
A14: TXN-1013 | B14: 45318 | C14: Netherlands | D14: Amsterdam | E14: CAT-102 | F14: Marketing & Advertising | G14: 4100
A15: TXN-1014 | B15: 45319 | C15: Japan | D15: Osaka | E15: CAT-103 | F15: Travel & Entertainment | G15: 2100.25
A16: TXN-1015 | B16: 45320 | C16: United States | D16: Chicago | E16: CAT-101 | F16: Cloud & IT Infrastructure | G16: 3890
A17: TXN-1016 | B17: 45321 | C17: Canada | D17: Vancouver | E17: CAT-106 | F17: Software Licenses | G17: 980
... A26: TXN-1025 | B26: 45330 | C26: United Kingdom | D26: London | E26: CAT-101 | F26: Cloud & IT Infrastructure | G26: 5950

Sheet text-join fun by hyphon
A1: TXN-1001 | B1: 45306 | C1: United States | D1: New York | E1: CAT-101 | F1: Cloud & IT Infrastructure | G1: 4250
A2: TXN-1002 | B2: 45307 | C2: United Kingdom | D2: London | E2: CAT-102 | F2: Marketing & Advertising | G2: 3100.5
A3: TXN-1003 | B3: 45308 | C3: Germany | D3: Berlin | E3: CAT-103 | F3: Travel & Entertainment | G3: 1240.75
A4: TXN-1004 | B4: 45309 | C4: Japan | D4: Tokyo | E4: CAT-106 | F4: Software Licenses | G4: 850
A5: TXN-1005 | B5: 45310 | C5: United States | D5: San Francisco | E5: CAT-105 | F5: Professional Services | G5: 6400
A6: TXN-1006 | B6: 45311 | C6: Canada | D6: Toronto | E6: CAT-104 | F6: Office Supplies | G6: 420.3
A7: TXN-1007 | B7: 45312 | C7: France | D7: Paris | E7: CAT-103 | F7: Travel & Entertainment | G7: 1850
A8: TXN-1008 | B8: 45313 | C8: Singapore | D8: Singapore | E8: CAT-101 | F8: Cloud & IT Infrastructure | G8: 5120
C12: =IFERROR(__xludf.DUMMYFUNCTION("TEXTJOIN(""="",,FILTER(D1:D8,C1:C8=""United States""))"),"New York=San Francisco") -> New York=San Francisco | G12: =IFERROR(__xludf.DUMMYFUNCTION("JOIN(""-"",G1:G4,G5:G8)"),"$4,250.00-$3,100.50-$1,240.75-$850.00-$6,400.00-$420.30-$1,850.00-$5,120.00") -> $4,250.00-$3,100.50-$1,240.75-$850.00-$6,400.00-$420.30-$1,850.00-$5,120.00

Sheet get cost by index-match of coun
A15: category | B15: United States | C15: Cloud & IT Infrastructure
A16: index | B16: =MATCH(B15,A3:A11) -> 9 | C16: =MATCH(C15,B2:G2) -> 1
A18: matched cost | B18: {=index(B3:G11,B16,C16)} -> 8140

Sheet specefic country cost by dropdo
A1: Transaction ID | B1: Date | C1: Country | D1: City | E1: Category ID | F1: Category Name | G1: Cost
A2: TXN-1001 | B2: 45306 | C2: United States | D2: New York | E2: CAT-101 | F2: Cloud & IT Infrastructure | G2: 4250 | L2: Find unique months in a data
A3: TXN-1002 | B3: 45307 | C3: United Kingdom | D3: London | E3: CAT-102 | F3: Marketing & Advertising | G3: 3100.5 | L3: =MONTH(B2:B26) -> 1 | M3: {=UNIQUE(L3:L26)} -> 1
A4: TXN-1003 | B4: 45308 | C4: Germany | D4: Berlin | E4: CAT-103 | F4: Travel & Entertainment | G4: 1240.75 | I4: {=UNIQUE(C2:C26)} -> United States | J4: Netherlands | L4: =MONTH(B3:B27) -> 1 | M4: 2
A5: TXN-1004 | B5: 45309 | C5: Japan | D5: Tokyo | E5: CAT-106 | F5: Software Licenses | G5: 850 | I5: United Kingdom | L5: =MONTH(B4:B28) -> 1
A6: TXN-1005 | B6: 45310 | C6: United States | D6: San Francisco | E6: CAT-105 | F6: Professional Services | G6: 6400 | I6: Germany | L6: =MONTH(B5:B29) -> 1 | M6: =IFERROR(__xludf.DUMMYFUNCTION("COUNTUNIQUE(L3:L26)"),2.0) -> 2
A7: TXN-1006 | B7: 45311 | C7: Canada | D7: Toronto | E7: CAT-104 | F7: Office Supplies | G7: 420.3 | I7: Japan | J7: =sumif(C2:C26,J4,G2:G26) -> 4640 | L7: =MONTH(B6:B30) -> 1
A8: TXN-1007 | B8: 45312 | C8: France | D8: Paris | E8: CAT-103 | F8: Travel & Entertainment | G8: 1850 | I8: Canada | L8: =MONTH(B7:B31) -> 1
A9: TXN-1008 | B9: 45313 | C9: Singapore | D9: Singapore | E9: CAT-101 | F9: Cloud & IT Infrastructure | G9: 5120 | I9: France | L9: =MONTH(B8:B32) -> 1
A10: TXN-1009 | B10: 45314 | C10: Australia | D10: Sydney | E10: CAT-102 | F10: Marketing & Advertising | G10: 2750 | I10: Singapore | L10: =MONTH(B9:B33) -> 1
A11: TXN-1010 | B11: 45315 | C11: United States | D11: Austin | E11: CAT-106 | F11: Software Licenses | G11: 1450 | I11: Australia | L11: =MONTH(B10:B34) -> 1
A12: TXN-1011 | B12: 45316 | C12: Germany | D12: Munich | E12: CAT-105 | F12: Professional Services | G12: 7200 | I12: Netherlands | L12: =MONTH(B11:B35) -> 1
A13: TXN-1012 | B13: 45317 | C13: United Kingdom | D13: Manchester | E13: CAT-104 | F13: Office Supplies | G13: 630.5 | L13: =MONTH(B12:B36) -> 1
A14: TXN-1013 | B14: 45318 | C14: Netherlands | D14: Amsterdam | E14: CAT-102 | F14: Marketing & Advertising | G14: 4100 | L14: =MONTH(B13:B37) -> 1
A15: TXN-1014 | B15: 45319 | C15: Japan | D15: Osaka | E15: CAT-103 | F15: Travel & Entertainment | G15: 2100.25 | L15: =MONTH(B14:B38) -> 1
A16: TXN-1015 | B16: 45320 | C16: United States | D16: Chicago | E16: CAT-101 | F16: Cloud & IT Infrastructure | G16: 3890 | L16: =MONTH(B15:B39) -> 1
A17: TXN-1016 | B17: 45321 | C17: Canada | D17: Vancouver | E17: CAT-106 | F17: Software Licenses | G17: 980 | L17: =MONTH(B16:B40) -> 1
A18: TXN-1017 | B18: 45322 | C18: United Kingdom | D18: London | E18: CAT-105 | F18: Professional Services | G18: 5500 | L18: =MONTH(B17:B41) -> 1
A19: TXN-1018 | B19: 45323 | C19: Australia | D19: Melbourne | E19: CAT-104 | F19: Office Supplies | G19: 315.8 | L19: =MONTH(B18:B42) -> 2
A20: TXN-1019 | B20: 45324 | C20: United States | D20: New York | E20: CAT-102 | F20: Marketing & Advertising | G20: 6800 | L20: =MONTH(B19:B43) -> 2
A21: TXN-1020 | B21: 45325 | C21: Germany | D21: Berlin | E21: CAT-101 | F21: Cloud & IT Infrastructure | G21: 4750 | L21: =MONTH(B20:B44) -> 2
A22: TXN-1021 | B22: 45326 | C22: France | D22: Paris | E22: CAT-105 | F22: Professional Services | G22: 3900 | L22: =MONTH(B21:B45) -> 2
A23: TXN-1022 | B23: 45327 | C23: Singapore | D23: Singapore | E23: CAT-103 | F23: Travel & Entertainment | G23: 1680.4 | L23: =MONTH(B22:B46) -> 2
A24: TXN-1023 | B24: 45328 | C24: United States | D24: San Francisco | E24: CAT-106 | F24: Software Licenses | G24: 2300 | L24: =MONTH(B23:B47) -> 2
... A26: TXN-1025 | B26: 45330 | C26: United Kingdom | D26: London | E26: CAT-101 | F26: Cloud & IT Infrastructure | G26: 5950 | L26: =MONTH(B25:B49) -> 2

Sheet Sheet4
A1: Transaction ID | B1: Date | C1: Country | D1: City | E1: Category ID | F1: Category Name | G1: Cost
A2: TXN-1001 | B2: 45306 | C2: United States | D2: New York | E2: CAT-101 | F2: Cloud & IT Infrastructure | G2: 4250
A3: TXN-1002 | B3: 45307 | C3: United Kingdom | D3: London | E3: CAT-102 | F3: Marketing & Advertising | G3: 3100.5
A4: TXN-1003 | B4: 45308 | C4: Germany | D4: Berlin | E4: CAT-103 | F4: Travel & Entertainment | G4: 1240.75
A5: TXN-1004 | B5: 45309 | C5: Japan | D5: Tokyo | E5: CAT-106 | F5: Software Licenses | G5: 850
A6: TXN-1005 | B6: 45310 | C6: United States | D6: San Francisco | E6: CAT-105 | F6: Professional Services | G6: 6400
A7: TXN-1006 | B7: 45311 | C7: Canada | D7: Toronto | E7: CAT-104 | F7: Office Supplies | G7: 420.3 | I7: {=unique(D:D)} -> City
A8: TXN-1007 | B8: 45312 | C8: France | D8: Paris | E8: CAT-103 | F8: Travel & Entertainment | G8: 1850 | I8: New York
A9: TXN-1008 | B9: 45313 | C9: Singapore | D9: Singapore | E9: CAT-101 | F9: Cloud & IT Infrastructure | G9: 5120 | I9: London
A10: TXN-1009 | B10: 45314 | C10: Australia | D10: Sydney | E10: CAT-102 | F10: Marketing & Advertising | G10: 2750 | I10: Berlin
A11: TXN-1010 | B11: 45315 | C11: United States | D11: Austin | E11: CAT-106 | F11: Software Licenses | G11: 1450 | I11: Tokyo
A12: TXN-1011 | B12: 45316 | C12: Germany | D12: Munich | E12: CAT-105 | F12: Professional Services | G12: 7200 | I12: San Francisco
A13: TXN-1012 | B13: 45317 | C13: United Kingdom | D13: Manchester | E13: CAT-104 | F13: Office Supplies | G13: 630.5 | I13: Toronto
A14: TXN-1013 | B14: 45318 | C14: Netherlands | D14: Amsterdam | E14: CAT-102 | F14: Marketing & Advertising | G14: 4100 | I14: Paris
A15: TXN-1014 | B15: 45319 | C15: Japan | D15: Osaka | E15: CAT-103 | F15: Travel & Entertainment | G15: 2100.25 | I15: Singapore
A16: TXN-1015 | B16: 45320 | C16: United States | D16: Chicago | E16: CAT-101 | F16: Cloud & IT Infrastructure | G16: 3890 | I16: Sydney
A17: TXN-1016 | B17: 45321 | C17: Canada | D17: Vancouver | E17: CAT-106 | F17: Software Licenses | G17: 980 | I17: Austin
A18: TXN-1017 | B18: 45322 | C18: United Kingdom | D18: London | E18: CAT-105 | F18: Professional Services | G18: 5500 | I18: Munich
A19: TXN-1018 | B19: 45323 | C19: Australia | D19: Melbourne | E19: CAT-104 | F19: Office Supplies | G19: 315.8 | I19: Manchester
... A24: TXN-1023 | B24: 45328 | C24: United States | D24: San Francisco | E24: CAT-106 | F24: Software Licenses | G24: 2300 | I24: Melbourne
A25: TXN-1024 | B25: 45329 | C25: Netherlands | D25: Amsterdam | E25: CAT-104 | F25: Office Supplies | G25: 540
A26: TXN-1025 | B26: 45330 | C26: United Kingdom | D26: London | E26: CAT-101 | F26: Cloud & IT Infrastructure | G26: 5950

Sheet Pivot Table 6

Sheet Specific city category Cost

Sheet Max Cost Country

Sheet Average Cost Per City

Sheet S2
A1: Category ID | B1: Category Name
A2: CAT-101 | B2: Cloud & IT Infrastructure
A3: CAT-102 | B3: Marketing & Advertising
A4: CAT-103 | B4: Travel & Entertainment
A5: CAT-106 | B5: Software Licenses
A6: CAT-105 | B6: Professional Services
A7: CAT-104 | B7: Office Supplies
A8: CAT-107 | B8: Travel & Entertainment
A9: CAT-108 | B9: Cloud & IT Infrastructure
A10: CAT-109 | B10: Marketing & Advertising
A11: CAT-110 | B11: Software Licenses
A12: CAT-111 | B12: Professional Services
... A26: CAT-101 | B26: Cloud & IT Infrastructure
